Workbook

Sheet 00_填写说明
A1: 微电网项目成本填报模板（明细版） / Microgrid Project Cost Input Template (Detailed)
A3: 这版模板适合新项目直接填报：支持同一系统下录入多个品牌/型号/子项，并自动汇总到 CAPEX 总表和项目看板。 / This version is designed for new projects and supports multiple brands, models, and sub-items under each system, with automatic roll-up to the CAPEX summary and project dashboard.
A5: 推荐填写顺序 / Recommended Input Sequence
A6: 1. 先在“01_项目基础信息”填写项目名称、国家、报价日期、系统规模。 / First fill in project name, country, quotation date, and system sizing in "01_项目基础信息".
A7: 2. CAPEX 先从“03_光伏系统明细”“04_储能系统明细”“05_柴油机系统明细”“06_电气配套明细”“07_运输安装其他”逐项填品牌、型号、数量和单价。 / Then fill CAPEX line by line in the PV, BESS, diesel, electrical, and logistics/installation detail sheets, including brand, model, quantity, and unit price.
A8: 3. 年度成本填“08_年度成本_OPEX”；柴油单价和假设填“09_柴油与能源参数”；柴油机维保参数填“10_柴油机维保参数”。 / Enter annual costs in "08_年度成本_OPEX", fuel assumptions in "09_柴油与能源参数", and diesel maintenance assumptions in "10_柴油机维保参数".
A9: 4. “02_CAPEX汇总”自动汇总各明细页合计；“11_汇总看板”用于最终检查是否漏项。 / "02_CAPEX汇总" automatically summarizes each detail sheet; "11_汇总看板" is used for final completeness checks.
A10: 补充说明：‘数量 / Qty’列只填写数字；单位请在‘数量单位 / Qty Unit’列填写或调整。币种请在‘币种 / Currency’列选择。 / Note: The Qty column should contain numbers only; units should be entered or adjusted in the Qty Unit column, and currency should be selected in the Currency column.
A11: 你可以怎么填/How can you fill it in
A12: • 光伏组件：同一项目如果有 2~3 种型号，可分 2~3 行分别填。PV Modules: If the same project includes 2–3 different module models, they can be listed in 2–3 separate rows.
A13: • 储能系统：建议拆成 PCS、电池包、电池柜/集装箱、BMS/EMS、HVAC/消防等子项。Energy Storage System: It is recommended to break it down into sub-items such as PCS, battery packs, battery cabinets/containers, BMS/EMS, HVAC/fire protection, etc.
A14: • 电气配套：建议把 AC 电缆、DC 电缆、开关柜、变压器、通信监控等分别列出。Electrical Balance of System (BOS): It is recommended to list items separately, such as AC cables, DC cables, switchgear, transformers, communication and monitoring systems, etc.
... A18: 颜色说明 / Color Legend
A19: 颜色 / Color | B19: 含义 / Meaning | C19: 建议怎么用 / How to Use | D19: 说明 / Notes
A20: 浅蓝 / Light Blue | B20: 输入区 / Input Area | C20: 直接填写 / Type directly | D20: 数量、单价、税费、备注等 / Qty, price, tax, remarks, etc.
A21: 浅绿 / Light Green | B21: 自动引用/参考 / Auto Link-Reference | C21: 对照检查 / Review against source | D21: 自动汇总、历史参考 / Auto roll-up, historical reference
A22: 浅黄 / Light Yellow | B22: 重点确认 / Key Check | C22: 优先检查 / Review first | D22: 项目基础信息、关键参数 / Project basics and key assumptions
A23: 白色 / White | B23: 公式或展示 / Formula-Display | C23: 一般不用改 / Usually do not edit | D23: 小计、合计、看板结果 / Subtotals, totals, dashboard results

Sheet 01_项目基础信息
A1: 项目基础信息（新项目先填） / Project Basic Information (Fill First)
A3: 项目信息 / Project Information
A4: 字段 / Field | B4: 填写值 / Input | C4: 重要程度 / Priority | D4: 说明 / Notes | E4: 来源/备注 / Source-Remarks | F4: 是否确认 / Confirmed
A5: 项目名称 / Project Name | B5: MGS微电网售前方案 | C5: 必填 / Required | D5: 例如：XX 微电网售前方案 / Example: XX Microgrid Proposal | F5: 否 / No
A6: 客户/业主 / Client-Owner | C6: 建议填 / Recommended | F6: 否 / No
A7: 国家/地区 / Country-Region | B7: 美国 | C7: 必填 / Required | D7: 例如：菲律宾 / 印尼 / 沙特 / Example: Philippines / Indonesia / Saudi Arabia | F7: 否 / No
A8: 具体站点 / Site | C8: 必填 / Required | D8: 经纬度/Latitude and longitude | F8: 否 / No
A9: 报价日期 / Quotation Date | B9: 46094 | C9: 必填 / Required | F9: 否 / No
A10: 项目阶段 / Project Stage | B10: 售前初算 / Early Estimate | C10: 建议填 / Recommended | F10: 否 / No
A12: 系统规模与关键假设 / System Size & Key Assumptions
A13: 字段 / Field | B13: 填写值 / Input | C13: 单位 / Unit | D13: 重要程度 / Priority | E13: 说明 / Notes | F13: 备注 / Remarks
A14: 光伏规模 / PV Size | B14: =0.655*32*4 -> 83.84 | C14: kWp | D14: 建议填 / Recommended
A15: 储能规模 / BESS Size | B15: =16*16080/1000 -> 257.28 | C15: kWh | D15: 建议填 / Recommended | E15: 建议填可用容量 / Enter usable energy if possible
A16: 柴油机容量 / Diesel Size | B16: 40 | C16: kW | D16: 选填 / Optional | E16: 如有多台机组可填合计 / Enter total if multiple gensets
A17: 负荷日均用电量 / Daily Energy Demand | B17: 360 | C17: 千瓦时/天 / kWh/day | D17: 选填 / Optional
A18: 设计年限 / Design Life | B18: 10 | C18: 年 / year | D18: 选填 / Optional | E18: 用于后续经济性测算 / Used for later economic analysis
A19: 基准币种 / Base Currency | B19: 美元 / USD | D19: 建议填 / Recommended | E19: 建议统一换算到 USD / Recommended to standardize to USD
A20: 税费口径说明 / Tax Basis Notes | D20: 选填 / Optional | E20: 例如：已含税 / 未含税 / Example: tax included / excluded
A21: 项目备注 / Project Notes | D21: 选填 / Optional

Sheet 02_CAPEX汇总
A1: CAPEX 汇总（自动引用各明细页） / CAPEX Summary (Auto-Linked from Detail Sheets)
A3: 这页只做检查和补充，不建议直接填总价。请尽量到各明细页按品牌/型号/子项逐行录入。 / This sheet is for review only. Please avoid entering lump-sum values directly here; instead, enter data line by line in the detail sheets by brand, model, and sub-item.
A4: 序号 / No. | B4: 成本模块 / Cost Module | C4: 引用来源 / Source Sheet | D4: 金额(USD) / Amount (USD) | E4: 检查说明 / Review Notes | F4: 是否确认 / Confirmed | G4: 备注 / Remarks | H4: 状态 / Status
A5: 1 | B5: 光伏系统 / PV System | C5: 03_光伏系统明细 | D5: =IF('03_光伏系统明细'!P13="","",'03_光伏系统明细'!P13) -> 125528.8 | E5: 是否已拆到组件/逆变器/支架 / Check if split to modules, inverters, mounting | F5: 否 / No
A6: 2 | B6: 储能系统 / BESS System | C6: 04_储能系统明细 | D6: =IF('04_储能系统明细'!P14="","",'04_储能系统明细'!P14) -> 53600 | E6: 是否已拆到 PCS/电池包/BMS 等 / Check if split to PCS, battery packs, BMS, etc. | F6: 否 / No
A7: 3 | B7: 柴油机系统 / Diesel System | C7: 05_柴油机系统明细 | D7: =IF('05_柴油机系统明细'!P11="","",'05_柴油机系统明细'!P11) -> 45000 | E7: 是否包含 ATS/油箱/排烟 / Check if ATS, tank, exhaust are included | F7: 否 / No
A8: 4 | B8: 电气配套 / Electrical Balance | C8: 06_电气配套明细 | D8: =IF('06_电气配套明细'!P13="","",'06_电气配套明细'!P13) -> 28200 | E8: 是否已拆到 AC/DC 电缆和开关柜 / Check if AC/DC cables and switchgear are split out | F8: 否 / No
A9: 5 | B9: 运输安装其他 / Logistics & Installation | C9: 07_运输安装其他 | D9: =IF('07_运输安装其他'!P13="","",'07_运输安装其他'!P13) -> 15800 | E9: 是否分开了运输/安装/调试 / Check if transport, installation, and commissioning are split | F9: 否 / No
A11: CAPEX 总计 / Total CAPEX | D11: =SUM(D5:D9) -> 268128.8 | E11: 来自五个 CAPEX 明细页 / From the five CAPEX detail sheets | F11: 否 / No

Sheet 03_光伏系统明细
A1: 光伏系统明细 / PV System Details
A3: 填写提示：同一系统下不同品牌/型号/子项请分行填写。小计(USD)=数量×单价×汇率×(1+税费率)+运费+其他调整。 / Guidance: Enter different brands/models/sub-items on separate lines. Subtotal (USD) = Qty × Unit Price × FX × (1+Tax Rate) + Freight + Other Adjustments.
A4: 序号 / No. | B4: 系统分类 / System | C4: 子类 / Subcategory | D4: 设备/成本项 / Item | E4: 品牌 / Brand | F4: 型号 / Model | G4: 规格/说明 / Specification-Description | H4: 数量单位 / Qty Unit | I4: 数量 / Qty | J4: 单价(原币) / Unit Price (Local) | K4: 币种 / Currency | L4: 汇率→USD / FX to USD | M4: 税费率 / Tax Rate | N4: 运费(USD) / Freight (USD) | O4: 其他调整(USD) / Other Adj. (USD) | P4: 小计(USD) / Subtotal (USD) | Q4: 价格来源/供应商 / Price Source-Supplier | R4: 备注 / Remarks | S4: 纳入总计? / Include?
A5: 1 | B5: 光伏系统 / PV System | C5: 组件 / Module | D5: 光伏组件 / PV Module | E5: 正泰/Astronergy | F5: ASTRO 6 Twins – CHSM66M(DG)/F-BH | G5: 655 | H5: Wp | I5: =4*32 -> 128 | J5: 209.6 | K5: 美元 / USD | L5: 1 | P5: =IF(OR(I5="",J5=""),"",I5*J5*IF(L5="",1,L5)*(1+IF(M5="",0,M5))+IF(N5="",0,N5)+IF(O5="",0,O5)) -> 26828.8 | Q5: 正泰/Astronergy | S5: 是 / Yes
A6: 2 | B6: 光伏系统 / PV System | C6: 组件 / Module | D6: 光伏组件 / PV Module | G6: 第二种型号可另起一行 / Use another row for a second model | H6: Wp | K6: 美元 / USD | L6: 1 | P6: =IF(OR(I6="",J6=""),"",I6*J6*IF(L6="",1,L6)*(1+IF(M6="",0,M6))+IF(N6="",0,N6)+IF(O6="",0,O6)) | S6: 否 / No
A7: 3 | B7: 光伏系统 / PV System | C7: 逆变器 / Inverter | D7: 组串逆变器 / String Inverter | E7: Sol-Ark | F7: Sol-Ark 18K 2P-N | G7: 18kW | H7: 套 / set | I7: 3 | J7: 7500 | K7: 美元 / USD | L7: 1 | P7: =IF(OR(I7="",J7=""),"",I7*J7*IF(L7="",1,L7)*(1+IF(M7="",0,M7))+IF(N7="",0,N7)+IF(O7="",0,O7)) -> 22500 | Q7: Sol-Ark | S7: 是 / Yes
A8: 4 | B8: 光伏系统 / PV System | C8: 逆变器 / Inverter | D8: 汇流箱 / Combine | H8: 套 / set | K8: 美元 / USD | L8: 1 | P8: =IF(OR(I8="",J8=""),"",I8*J8*IF(L8="",1,L8)*(1+IF(M8="",0,M8))+IF(N8="",0,N8)+IF(O8="",0,O8)) | S8: 否 / No
A9: 5 | B9: 光伏系统 / PV System | C9: 支架 / Mounting | D9: 光伏支架 / PV Mounting | E9: 自研/Proprietary equipment | H9: 套 / set | I9: 4 | J9: =12700 -> 12700 | K9: 美元 / USD | L9: 1 | M9: 0.5 | P9: =IF(OR(I9="",J9=""),"",I9*J9*IF(L9="",1,L9)*(1+IF(M9="",0,M9))+IF(N9="",0,N9)+IF(O9="",0,O9)) -> 76200 | Q9: voltage energy | S9: 是 / Yes
A10: 6 | B10: 光伏系统 / PV System | C10: 连接器/辅材 / Connectors-Auxiliary | D10: 连接器/MC4 / Connectors-MC4 | H10: 项 / lot | K10: 美元 / USD | L10: 1 | P10: =IF(OR(I10="",J10=""),"",I10*J10*IF(L10="",1,L10)*(1+IF(M10="",0,M10))+IF(N10="",0,N10)+IF(O10="",0,O10)) | S10: 否 / No
A11: 7 | B11: 光伏系统 / PV System | C11: 连接器/辅材 / Connectors-Auxiliary | D11: 直流汇流/线盒 / DC Combiner-Junction Box | H11: 项 / lot | K11: 美元 / USD | L11: 1 | P11: =IF(OR(I11="",J11=""),"",I11*J11*IF(L11="",1,L11)*(1+IF(M11="",0,M11))+IF(N11="",0,N11)+IF(O11="",0,O11)) | S11: 否 / No
A12: 8 | B12: 光伏系统 / PV System | C12: 连接器/辅材 / Connectors-Auxiliary | D12: 其他光伏辅材 / Other PV Auxiliary | H12: 项 / lot | K12: 美元 / USD | L12: 1 | P12: =IF(OR(I12="",J12=""),"",I12*J12*IF(L12="",1,L12)*(1+IF(M12="",0,M12))+IF(N12="",0,N12)+IF(O12="",0,O12)) | S12: 否 / No
A13: 合计 / Total | P13: =SUMIFS($P$5:$P$12,$S$5:$S$12,"是 / Yes") -> 125528.8 | Q13: 仅统计“纳入总计?=是 / Yes”的行 / Only rows marked "Include? = Yes" are counted

Sheet 04_储能系统明细
A1: 储能系统明细 / BESS System Details
A3: 填写提示：同一系统下不同品牌/型号/子项请分行填写。小计(USD)=数量×单价×汇率×(1+税费率)+运费+其他调整。 / Guidance: Enter different brands/models/sub-items on separate lines. Subtotal (USD) = Qty × Unit Price × FX × (1+Tax Rate) + Freight + Other Adjustments.
A4: 序号 / No. | B4: 系统分类 / System | C4: 子类 / Subcategory | D4: 设备/成本项 / Item | E4: 品牌 / Brand | F4: 型号 / Model | G4: 规格/说明 / Specification-Description | H4: 数量单位 / Qty Unit | I4: 数量 / Qty | J4: 单价(原币) / Unit Price (Local) | K4: 币种 / Currency | L4: 汇率→USD / FX to USD | M4: 税费率 / Tax Rate | N4: 运费(USD) / Freight (USD) | O4: 其他调整(USD) / Other Adj. (USD) | P4: 小计(USD) / Subtotal (USD) | Q4: 价格来源/供应商 / Price Source-Supplier | R4: 备注 / Remarks | S4: 纳入总计? / Include?
A5: 1 | B5: 储能系统 / BESS System | C5: PCS / PCS | D5: 储能变流器 PCS / PCS | G5: 如：250kW/500kW / e.g. 250kW/500kW | H5: 套 / set | K5: 美元 / USD | L5: 1 | P5: =IF(OR(I5="",J5=""),"",I5*J5*IF(L5="",1,L5)*(1+IF(M5="",0,M5))+IF(N5="",0,N5)+IF(O5="",0,O5)) | S5: 否 / No
A6: 2 | B6: 储能系统 / BESS System | C6: 电池包 / Battery Pack | D6: 电池包/模组 / Battery Pack-Module | E6: Discover Energy Systems | F6: HELIOS ESS 52-48-16000 | G6: 16.08 kWh | H6: pack | I6: 16 | J6: 3100 | K6: 美元 / USD | L6: 1 | P6: =IF(OR(I6="",J6=""),"",I6*J6*IF(L6="",1,L6)*(1+IF(M6="",0,M6))+IF(N6="",0,N6)+IF(O6="",0,O6)) -> 49600 | Q6: Discover Energy Systems | S6: 是 / Yes
A7: 3 | B7: 储能系统 / BESS System | C7: 光储一体化托盘/PV-ESS Integrated Pallet | D7: 一体化托盘/Integrated pallet | E7: 自研/Proprietary equipment | H7: 套 / set | I7: 1 | J7: 4000 | K7: 美元 / USD | L7: 1 | P7: =IF(OR(I7="",J7=""),"",I7*J7*IF(L7="",1,L7)*(1+IF(M7="",0,M7))+IF(N7="",0,N7)+IF(O7="",0,O7)) -> 4000 | Q7: voltage energy | S7: 是 / Yes
A8: 3 | B8: 储能系统 / BESS System | C8: 电池柜/集装箱 / Battery Cabinet-Container | D8: 电池柜/电池簇 / Battery Cabinet-String | H8: 套 / set | K8: 美元 / USD | L8: 1 | P8: =IF(OR(I8="",J8=""),"",I8*J8*IF(L8="",1,L8)*(1+IF(M8="",0,M8))+IF(N8="",0,N8)+IF(O8="",0,O8)) | S8: 否 / No
A9: 4 | B9: 储能系统 / BESS System | C9: BMS/EMS / BMS-EMS | D9: BMS / BMS | H9: 套 / set | K9: 美元 / USD | L9: 1 | P9: =IF(OR(I9="",J9=""),"",I9*J9*IF(L9="",1,L9)*(1+IF(M9="",0,M9))+IF(N9="",0,N9)+IF(O9="",0,O9)) | S9: 否 / No
A10: 5 | B10: 储能系统 / BESS System | C10: BMS/EMS / BMS-EMS | D10: EMS/能量管理 / EMS-Energy Management | H10: 套 / set | K10: 美元 / USD | L10: 1 | P10: =IF(OR(I10="",J10=""),"",I10*J10*IF(L10="",1,L10)*(1+IF(M10="",0,M10))+IF(N10="",0,N10)+IF(O10="",0,O10)) | S10: 否 / No
A11: 6 | B11: 储能系统 / BESS System | C11: HVAC/消防 / HVAC-Fire | D11: 空调/HVAC / HVAC | H11: 套 / set | K11: 美元 / USD | L11: 1 | P11: =IF(OR(I11="",J11=""),"",I11*J11*IF(L11="",1,L11)*(1+IF(M11="",0,M11))+IF(N11="",0,N11)+IF(O11="",0,O11)) | S11: 否 / No
A12: 7 | B12: 储能系统 / BESS System | C12: HVAC/消防 / HVAC-Fire | D12: 消防系统 / Fire Suppression | H12: 套 / set | K12: 美元 / USD | L12: 1 | P12: =IF(OR(I12="",J12=""),"",I12*J12*IF(L12="",1,L12)*(1+IF(M12="",0,M12))+IF(N12="",0,N12)+IF(O12="",0,O12)) | S12: 否 / No
A13: 8 | B13: 储能系统 / BESS System | C13: 连接器/辅材 / Connectors-Auxiliary | D13: 储能辅材/铜排 / BESS Auxiliary-Busbar | H13: 项 / lot | I13: 1 | J13: 300 | K13: 美元 / USD | L13: 1 | P13: =IF(OR(I13="",J13=""),"",I13*J13*IF(L13="",1,L13)*(1+IF(M13="",0,M13))+IF(N13="",0,N13)+IF(O13="",0,O13)) -> 300 | S13: 否 / No
A14: 合计 / Total | P14: =SUMIFS($P$5:$P$13,$S$5:$S$13,"是 / Yes") -> 53600 | Q14: 仅统计“纳入总计?=是 / Yes”的行 / Only rows marked "Include? = Yes" are counted

Sheet 05_柴油机系统明细
A1: 柴油机系统明细 / Diesel System Details
A3: 填写提示：同一系统下不同品牌/型号/子项请分行填写。小计(USD)=数量×单价×汇率×(1+税费率)+运费+其他调整。 / Guidance: Enter different brands/models/sub-items on separate lines. Subtotal (USD) = Qty × Unit Price × FX × (1+Tax Rate) + Freight + Other Adjustments.
A4: 序号 / No. | B4: 系统分类 / System | C4: 子类 / Subcategory | D4: 设备/成本项 / Item | E4: 品牌 / Brand | F4: 型号 / Model | G4: 规格/说明 / Specification-Description | H4: 数量单位 / Qty Unit | I4: 数量 / Qty | J4: 单价(原币) / Unit Price (Local) | K4: 币种 / Currency | L4: 汇率→USD / FX to USD | M4: 税费率 / Tax Rate | N4: 运费(USD) / Freight (USD) | O4: 其他调整(USD) / Other Adj. (USD) | P4: 小计(USD) / Subtotal (USD) | Q4: 价格来源/供应商 / Price Source-Supplier | R4: 备注 / Remarks | S4: 纳入总计? / Include?
A5: 1 | B5: 柴油机系统 / Diesel System | C5: 柴油发电机 / Diesel Generator | D5: 柴油发电机组 / Diesel Generator Set | G5: 40kW | H5: 套 / set | I5: 1 | J5: 45000 | K5: 美元 / USD | L5: 1 | P5: =IF(OR(I5="",J5=""),"",I5*J5*IF(L5="",1,L5)*(1+IF(M5="",0,M5))+IF(N5="",0,N5)+IF(O5="",0,O5)) -> 45000 | S5: 是 / Yes
A6: 2 | B6: 柴油机系统 / Diesel System | C6: 油箱/ATS / Tank-ATS | D6: ATS/并机柜 / ATS-Paralleling Panel | H6: 套 / set | K6: 美元 / USD | L6: 1 | P6: =IF(OR(I6="",J6=""),"",I6*J6*IF(L6="",1,L6)*(1+IF(M6="",0,M6))+IF(N6="",0,N6)+IF(O6="",0,O6)) | S6: 否 / No
A7: 3 | B7: 柴油机系统 / Diesel System | C7: 油箱/ATS / Tank-ATS | D7: 日用油箱/底座油箱 / Day Tank-Base Tank | H7: 套 / set | K7: 美元 / USD | L7: 1 | P7: =IF(OR(I7="",J7=""),"",I7*J7*IF(L7="",1,L7)*(1+IF(M7="",0,M7))+IF(N7="",0,N7)+IF(O7="",0,O7)) | S7: 否 / No
A8: 4 | B8: 柴油机系统 / Diesel System | C8: 油箱/ATS / Tank-ATS | D8: 排烟/消音系统 / Exhaust-Silencer | H8: 套 / set | K8: 美元 / USD | L8: 1 | P8: =IF(OR(I8="",J8=""),"",I8*J8*IF(L8="",1,L8)*(1+IF(M8="",0,M8))+IF(N8="",0,N8)+IF(O8="",0,O8)) | S8: 否 / No
A9: 5 | B9: 柴油机系统 / Diesel System | C9: 连接器/辅材 / Connectors-Auxiliary | D9: 启动电池/充电器 / Starter Battery-Charger | H9: 套 / set | K9: 美元 / USD | L9: 1 | P9: =IF(OR(I9="",J9=""),"",I9*J9*IF(L9="",1,L9)*(1+IF(M9="",0,M9))+IF(N9="",0,N9)+IF(O9="",0,O9)) | S9: 否 / No
A10: 6 | B10: 柴油机系统 / Diesel System | C10: 连接器/辅材 / Connectors-Auxiliary | D10: 柴油机辅材 / Diesel Auxiliary | H10: 项 / lot | K10: 美元 / USD | L10: 1 | P10: =IF(OR(I10="",J10=""),"",I10*J10*IF(L10="",1,L10)*(1+IF(M10="",0,M10))+IF(N10="",0,N10)+IF(O10="",0,O10)) | S10: 否 / No
A11: 合计 / Total | P11: =SUMIFS($P$5:$P$10,$S$5:$S$10,"是 / Yes") -> 45000 | Q11: 仅统计“纳入总计?=是 / Yes”的行 / Only rows marked "Include? = Yes" are counted

Sheet 06_电气配套明细
A1: 电气配套明细 / Electrical Balance Details
A3: 填写提示：同一系统下不同品牌/型号/子项请分行填写。小计(USD)=数量×单价×汇率×(1+税费率)+运费+其他调整。 / Guidance: Enter different brands/models/sub-items on separate lines. Subtotal (USD) = Qty × Unit Price × FX × (1+Tax Rate) + Freight + Other Adjustments.
A4: 序号 / No. | B4: 系统分类 / System | C4: 子类 / Subcategory | D4: 设备/成本项 / Item | E4: 品牌 / Brand | F4: 型号 / Model | G4: 规格/说明 / Specification-Description | H4: 数量单位 / Qty Unit | I4: 数量 / Qty | J4: 单价(原币) / Unit Price (Local) | K4: 币种 / Currency | L4: 汇率→USD / FX to USD | M4: 税费率 / Tax Rate | N4: 运费(USD) / Freight (USD) | O4: 其他调整(USD) / Other Adj. (USD) | P4: 小计(USD) / Subtotal (USD) | Q4: 价格来源/供应商 / Price Source-Supplier | R4: 备注 / Remarks | S4: 纳入总计? / Include?
A5: 1 | B5: 电气配套 / Electrical Balance | C5: 开关柜 / Switchgear | D5: 低压开关柜/配电柜 / LV Switchboard-Distribution Panel | H5: 套 / set | I5: 1 | J5: 26000 | K5: 美元 / USD | L5: 1 | P5: =IF(OR(I5="",J5=""),"",I5*J5*IF(L5="",1,L5)*(1+IF(M5="",0,M5))+IF(N5="",0,N5)+IF(O5="",0,O5)) -> 26000 | S5: 是 / Yes
A6: 2 | B6: 电气配套 / Electrical Balance | C6: 变压器 / Transformer | D6: 变压器 / Transformer | H6: 套 / set | K6: 美元 / USD | L6: 1 | P6: =IF(OR(I6="",J6=""),"",I6*J6*IF(L6="",1,L6)*(1+IF(M6="",0,M6))+IF(N6="",0,N6)+IF(O6="",0,O6)) | S6: 否 / No
A7: 3 | B7: 电气配套 / Electrical Balance | C7: AC电缆 / AC Cable | D7: 交流电缆 / AC Cable | G7: 可按回路分行 / Split by feeder if needed | H7: 米 / m | I7: 1 | J7: 200 | K7: 美元 / USD | L7: 1 | P7: =IF(OR(I7="",J7=""),"",I7*J7*IF(L7="",1,L7)*(1+IF(M7="",0,M7))+IF(N7="",0,N7)+IF(O7="",0,O7)) -> 200 | S7: 是 / Yes
A8: 4 | B8: 电气配套 / Electrical Balance | C8: DC电缆 / DC Cable | D8: 直流电缆 / DC Cable | G8: 可按规格分行 / Split by size if needed | H8: 米 / m | I8: 1 | J8: 2000 | K8: 美元 / USD | L8: 1 | P8: =IF(OR(I8="",J8=""),"",I8*J8*IF(L8="",1,L8)*(1+IF(M8="",0,M8))+IF(N8="",0,N8)+IF(O8="",0,O8)) -> 2000 | S8: 是 / Yes
A9: 5 | B9: 电气配套 / Electrical Balance | C9: 接地防雷 / Grounding-Lightning | D9: 接地与防雷 / Grounding & Lightning | H9: 项 / lot | K9: 美元 / USD | L9: 1 | P9: =IF(OR(I9="",J9=""),"",I9*J9*IF(L9="",1,L9)*(1+IF(M9="",0,M9))+IF(N9="",0,N9)+IF(O9="",0,O9)) | S9: 否 / No
A10: 6 | B10: 电气配套 / Electrical Balance | C10: 通信监控 / Communication-SCADA | D10: 通信监控/SCADA / Communication-SCADA | H10: 套 / set | K10: 美元 / USD | L10: 1 | P10: =IF(OR(I10="",J10=""),"",I10*J10*IF(L10="",1,L10)*(1+IF(M10="",0,M10))+IF(N10="",0,N10)+IF(O10="",0,O10)) | S10: 否 / No
A11: 7 | B11: 电气配套 / Electrical Balance | C11: 连接器/辅材 / Connectors-Auxiliary | D11: 桥架/线槽/端子 / Cable Tray-Trunking-Terminals | H11: 项 / lot | K11: 美元 / USD | L11: 1 | P11: =IF(OR(I11="",J11=""),"",I11*J11*IF(L11="",1,L11)*(1+IF(M11="",0,M11))+IF(N11="",0,N11)+IF(O11="",0,O11)) | S11: 否 / No
A12: 8 | B12: 电气配套 / Electrical Balance | C12: 连接器/辅材 / Connectors-Auxiliary | D12: 其他电气配套 / Other Electrical Balance | H12: 项 / lot | K12: 美元 / USD | L12: 1 | P12: =IF(OR(I12="",J12=""),"",I12*J12*IF(L12="",1,L12)*(1+IF(M12="",0,M12))+IF(N12="",0,N12)+IF(O12="",0,O12)) | S12: 否 / No
A13: 合计 / Total | P13: =SUMIFS($P$5:$P$12,$S$5:$S$12,"是 / Yes") -> 28200 | Q13: 仅统计“纳入总计?=是 / Yes”的行 / Only rows marked "Include? = Yes" are counted

Sheet 07_运输安装其他
A1: 运输安装其他明细 / Logistics & Installation Details
A3: 填写提示：同一系统下不同品牌/型号/子项请分行填写。小计(USD)=数量×单价×汇率×(1+税费率)+运费+其他调整。 / Guidance: Enter different brands/models/sub-items on separate lines. Subtotal (USD) = Qty × Unit Price × FX × (1+Tax Rate) + Freight + Other Adjustments.
A4: 序号 / No. | B4: 系统分类 / System | C4: 子类 / Subcategory | D4: 设备/成本项 / Item | E4: 品牌 / Brand | F4: 型号 / Model | G4: 规格/说明 / Specification-Description | H4: 数量单位 / Qty Unit | I4: 数量 / Qty | J4: 单价(原币) / Unit Price (Local) | K4: 币种 / Currency | L4: 汇率→USD / FX to USD | M4: 税费率 / Tax Rate | N4: 运费(USD) / Freight (USD) | O4: 其他调整(USD) / Other Adj. (USD) | P4: 小计(USD) / Subtotal (USD) | Q4: 价格来源/供应商 / Price Source-Supplier | R4: 备注 / Remarks | S4: 纳入总计? / Include?
A5: 1 | B5: 运输安装其他 / Logistics & Installation | C5: 运输 / Transportation | D5: 国际运输 / International Transportation | H5: 项 / lot | I5: 3 | J5: 3600 | K5: 美元 / USD | L5: 1 | P5: =IF(OR(I5="",J5=""),"",I5*J5*IF(L5="",1,L5)*(1+IF(M5="",0,M5))+IF(N5="",0,N5)+IF(O5="",0,O5)) -> 10800 | S5: 是 / Yes
A6: 2 | B6: 运输安装其他 / Logistics & Installation | C6: 运输 / Transportation | D6: 国内/内陆运输 / Domestic-Inland Transportation | H6: 项 / lot | K6: 美元 / USD | L6: 1 | P6: =IF(OR(I6="",J6=""),"",I6*J6*IF(L6="",1,L6)*(1+IF(M6="",0,M6))+IF(N6="",0,N6)+IF(O6="",0,O6)) | S6: 否 / No
A7: 3 | B7: 运输安装其他 / Logistics & Installation | C7: 安装 / Installation | D7: 安装人工 / Installation Labor | H7: 项 / lot | I7: 10 | J7: 500 | K7: 美元 / USD | L7: 1 | P7: =IF(OR(I7="",J7=""),"",I7*J7*IF(L7="",1,L7)*(1+IF(M7="",0,M7))+IF(N7="",0,N7)+IF(O7="",0,O7)) -> 5000 | R7: 估算 | S7: 是 / Yes
A8: 4 | B8: 运输安装其他 / Logistics & Installation | C8: 调试 / Commissioning | D8: 调试/试运行 / Commissioning-Test Run | H8: 项 / lot | K8: 美元 / USD | L8: 1 | P8: =IF(OR(I8="",J8=""),"",I8*J8*IF(L8="",1,L8)*(1+IF(M8="",0,M8))+IF(N8="",0,N8)+IF(O8="",0,O8)) | S8: 否 / No
A9: 5 | B9: 运输安装其他 / Logistics & Installation | C9: 安装 / Installation | D9: 吊装/叉车/机具 / Crane-Forklift-Tools | H9: 项 / lot | K9: 美元 / USD | L9: 1 | P9: =IF(OR(I9="",J9=""),"",I9*J9*IF(L9="",1,L9)*(1+IF(M9="",0,M9))+IF(N9="",0,N9)+IF(O9="",0,O9)) | S9: 否 / No
A10: 6 | B10: 运输安装其他 / Logistics & Installation | C10: 关税/清关 /Customs Clearance | D10: 清关/报关 / Customs Clearance | H10: 项 / lot | K10: 美元 / USD | L10: 1 | P10: =IF(OR(I10="",J10=""),"",I10*J10*IF(L10="",1,L10)*(1+IF(M10="",0,M10))+IF(N10="",0,N10)+IF(O10="",0,O10)) | S10: 否 / No
A11: 7 | B11: 运输安装其他 / Logistics & Installation | C11: 其他 / Other | D11: 差旅/住宿 / Travel-Accommodation | H11: 项 / lot | K11: 美元 / USD | L11: 1 | P11: =IF(OR(I11="",J11=""),"",I11*J11*IF(L11="",1,L11)*(1+IF(M11="",0,M11))+IF(N11="",0,N11)+IF(O11="",0,O11)) | S11: 否 / No
A12: 8 | B12: 运输安装其他 / Logistics & Installation | C12: 其他 / Other | D12: 预备费/其他调整 / Contingency-Other Adjustment | H12: 项 / lot | K12: 美元 / USD | L12: 1 | P12: =IF(OR(I12="",J12=""),"",I12*J12*IF(L12="",1,L12)*(1+IF(M12="",0,M12))+IF(N12="",0,N12)+IF(O12="",0,O12)) | S12: 否 / No
A13: 合计 / Total | P13: =SUMIFS($P$5:$P$12,$S$5:$S$12,"是 / Yes") -> 15800 | Q13: 仅统计“纳入总计?=是 / Yes”的行 / Only rows marked "Include? = Yes" are counted

Sheet 08_年度成本_OPEX
A1: 年度成本（OPEX）录入 / Annual Cost (OPEX) Input
A3: 柴油机年度保养会自动根据 09 页运行小时和 10 页维保参数测算；其他年度费用仍可手工填写。 / Annual diesel maintenance is auto-calculated from runtime on Sheet 09 and maintenance parameters on Sheet 10; other annual costs can still be entered manually.
A4: 序号 / No. | B4: 成本分类 / Cost Category | C4: 子类 / Subcategory | D4: 成本项目 / Cost Item | E4: 计算口径/说明 / Basis-Description | F4: 数量单位 / Qty Unit | G4: 数量/频次 / Qty-Frequency | H4: 单价(原币) / Unit Price (Local) | I4: 币种 / Currency | J4: 汇率→USD / FX to USD | K4: 年费用(USD) / Annual Cost (USD) | L4: 来源/依据 / Source-Basis | M4: 备注 / Remarks | N4: 纳入总计? / Include?
A5: 1 | B5: 年度固定运维 / Annual Fixed O&M | C5: 运维 / O&M | D5: 微电网运维费用 / Microgrid O&M | E5: 固定年费 / Fixed Annual Fee | F5: 年 / year | G5: 1 | H5: 1000 | I5: 美元 / USD | J5: 1 | K5: =IF(OR(G5="",H5=""),"",G5*H5*IF(J5="",1,J5)) -> 1000 | N5: 是 / Yes
A6: 2 | B6: 年度固定运维 / Annual Fixed O&M | C6: 维修 / Repair | D6: 设备维修费用 / Equipment Repair | E6: 固定年费 / Fixed Annual Fee | F6: 年 / year | G6: 1 | H6: 200 | I6: 美元 / USD | J6: 1 | K6: =IF(OR(G6="",H6=""),"",G6*H6*IF(J6="",1,J6)) -> 200 | N6: 是 / Yes
A7: 3 | B7: 年度固定运维 / Annual Fixed O&M | C7: 保险 / Insurance | D7: 保险费用 / Insurance | E7: 固定年费 / Fixed Annual Fee | F7: 年 / year | G7: 1 | H7: 3000 | I7: 美元 / USD | J7: 1 | K7: =IF(OR(G7="",H7=""),"",G7*H7*IF(J7="",1,J7)) -> 3000 | N7: 是 / Yes
A8: 4 | B8: 年度固定运维 / Annual Fixed O&M | C8: 维保 / Maintenance | D8: 柴油机年度保养 / Annual Diesel Maintenance | E8: 自动计算：运行小时+维保参数 / Auto calc: runtime + maintenance params | F8: 年 / year | G8: 1 | H8: =IF('10_柴油机维保参数'!E31="","",'10_柴油机维保参数'!E31) -> 738.1 | I8: 美元 / USD | J8: 1 | K8: =IF(OR(G8="",H8=""),"",G8*H8*IF(J8="",1,J8)) -> 738.1 | L8: 自动引用 09+10 页 / Auto-linked from Sheets 09+10 | M8: 空白时取默认值 / Blank uses default | N8: 是 / Yes
A9: 5 | B9: 年度固定运维 / Annual Fixed O&M | C9: 通信 / Communication | D9: 远程监控/通信 / Remote Monitoring-Communication | E9: 固定年费 / Fixed Annual Fee | F9: 年 / year | G9: 1 | I9: 美元 / USD | J9: 1 | K9: =IF(OR(G9="",H9=""),"",G9*H9*IF(J9="",1,J9)) | N9: 否 / No
A10: 6 | B10: 年度固定运维 / Annual Fixed O&M | C10: 租赁/土地 / Lease-Land | D10: 场地租赁/地租 / Site Lease-Land Rent | E10: 固定年费 / Fixed Annual Fee | F10: 年 / year | G10: 1 | I10: 美元 / USD | J10: 1 | K10: =IF(OR(G10="",H10=""),"",G10*H10*IF(J10="",1,J10)) | N10: 否 / No
A11: 7 | B11: 年度固定运维 / Annual Fixed O&M | C11: 其他 / Other | D11: 其他年度费用 / Other Annual Cost | F11: 年 / year | I11: 美元 / USD | J11: 1 | K11: =IF(OR(G11="",H11=""),"",G11*H11*IF(J11="",1,J11)) | N11: 否 / No
A12: OPEX 合计 | K12: =SUMIFS(K5:K11,N5:N11,"是 / Yes") -> 4938.1

Sheet 09_柴油与能源参数
A1: 柴油与能源参数 / Fuel & Energy Parameters
A3: 建议至少填写柴油单价和柴油机预计年运行小时；其中年运行小时会参与柴油机年度保养自动测算。 / At minimum, fill in diesel price and estimated annual diesel runtime; runtime feeds the auto-calculation of annual diesel maintenance.
A4: 序号 / No. | B4: 参数分类 / Parameter Category | C4: 参数名称 / Parameter | D4: 参数单位 / Unit | E4: 参数值 / Value | F4: 重要程度 / Priority | G4: 说明/备注 / Notes
A5: 1 | B5: 燃料参数 / Fuel | C5: 柴油单价 / Diesel Price | D5: 美元/升 / USD/L | E5: 0.95 | F5: 必填 / Required | G5: 历史项目参考值为 0.95 USD/L
A6: 2 | B6: 燃料参数 / Fuel | C6: 柴油到站额外运费 / Delivered Fuel Adder | D6: 美元/升 / USD/L | F6: 选填 / Optional | G6: 已含在油价时可留空
A7: 3 | B7: 运行口径 / Operating Basis | C7: 柴油机预计年运行小时 / Estimated Annual Diesel Runtime | D7: 小时/年 / h/year | E7: 500 | F7: 建议填 / Recommended | G7: 可用于估算保养频次
A8: 4 | B8: 运行口径 / Operating Basis | C8: 柴油机平均负载率 / Average Diesel Load Factor | D8: 百分比 / % | F8: 选填 / Optional | G8: 例如 30%~80%
A9: 5 | B9: 运行口径 / Operating Basis | C9: 预计年耗油量 / Estimated Annual Fuel Use | D9: L/year | F9: 选填 / Optional | G9: 已有经验值时可填
A10: 6 | B10: 运行口径 / Operating Basis | C10: 油价敏感性上浮 / Fuel Price Upside Sensitivity | D10: 百分比 / % | F10: 选填 / Optional | G10: 例如 10%

Sheet 10_柴油机维保参数
A1: 柴油发电机维保参数 / Diesel Maintenance Parameters
A3: 建议先沿用默认值，再按机组型号、人工单价或地区修正；“本项目调整后”优先用于柴油机年度保养自动计算。 / Start with defaults, then adjust for genset model, labor rate, or region; 'Adjusted for This Project' takes precedence in annual diesel maintenance auto-calculation.
A4: 序号 / No. | B4: 参数名称 / Parameter | C4: 参数代码 / Code | D4: 参数单位 / Unit | E4: 默认值 / Default | F4: 重要程度 / Priority | G4: 说明 / Notes | H4: 本项目调整后 / Adjusted for This Project
A5: 1 | B5: 小保养间隔 / Minor Service Interval | C5: S_oil | D5: 小时 / h | E5: 250 | F5: 建议填 / Recommended | G5: 每隔该小时执行小保养 / Minor service every N hours
A6: 2 | B6: 每次保养工时 / Labor Hours per Service | C6: t_pm | D6: 小时 / h | E6: 1.5 | F6: 建议填 / Recommended | G6: 小保养人工时 / Labor hours for minor service
A7: 3 | B7: 每次换油量 / Oil Volume per Service | C7: V_oil | D7: 加仑 / gal | E7: 2.15 | F7: 建议填 / Recommended | G7: 每次更换机油量 / Oil replaced each service
A8: 4 | B8: 机油单价 / Engine Oil Unit Price | C8: P_oil | D8: 美元/加仑 / USD/gal | E8: 22 | F8: 建议填 / Recommended | G8: 机油单价 / Unit price of engine oil
A9: 5 | B9: 机油滤芯价格 / Oil Filter Cost | C9: C_of | D9: 美元 / USD | E9: 18 | F9: 建议填 / Recommended
A10: 6 | B10: 柴油滤芯价格 / Fuel Filter Cost | C10: C_ff | D10: 美元 / USD | E10: 20 | F10: 建议填 / Recommended
A11: 7 | B11: 空气滤芯价格 / Air Filter Cost | C11: C_af | D11: 美元 / USD | E11: 30 | F11: 建议填 / Recommended | G11: 默认每 2 次 PM 换 1 只 / Default: one filter every 2 PM services
A12: 8 | B12: 人工费率 / Labor Rate | C12: labor_rate | D12: 美元/小时 / USD/h | E12: 125 | F12: 建议填 / Recommended | G12: 维保人工费率 / Maintenance labor rate
A13: 9 | B13: 空滤间隔 / Air Filter Interval | C13: S_air | D13: 小时 / h | E13: 500 | F13: 选填 / Optional | G13: 参考每 2 次保养换 1 只 / Reference: replace every 2 services
A14: 10 | B14: 冷却液周期 / Coolant Replacement Interval | C14: coolant_interval_years | D14: 年 / year | E14: 2 | F14: 选填 / Optional | G14: 每 N 年更换一次 / Replace every N years
A15: 11 | B15: 冷却液量 / Coolant Volume | C15: coolant_gal_per_service | D15: 加仑 / gal | E15: 2 | F15: 选填 / Optional | G15: 每次更换体积 / Volume per service
A16: 12 | B16: 冷却液单价 / Coolant Unit Price | C16: P_coolant | D16: 美元/加仑 / USD/gal | E16: 15 | F16: 选填 / Optional
A17: 13 | B17: 冷却液工时 / Coolant Labor Hours | C17: t_coolant | D17: 小时 / h | E17: 1 | F17: 选填 / Optional
A18: 14 | B18: 启动电池更换周期 / Starter Battery Interval | C18: battery_interval_years | D18: 年 / year | E18: 2 | F18: 选填 / Optional | G18: 每 N 年更换一次 / Replace every N years
A19: 15 | B19: 启动电池价格 / Starter Battery Cost | C19: C_start_battery | D19: 美元 / USD | E19: 70 | F19: 选填 / Optional
A20: 16 | B20: 启动电池更换工时 / Starter Battery Labor Hours | C20: t_battery | D20: 小时 / h | E20: 0.8 | F20: 选填 / Optional
A23: 自动测算结果 / Auto Calculated Outputs
A24: 计算项 / Calculated Item | E24: 数值 / Value
A25: 预计年运行小时 / Annual Runtime | E25: =IF('09_柴油与能源参数'!E7="","",'09_柴油与能源参数'!E7) -> 500
A26: 年小保养次数 / Minor Services per Year | E26: =IF(E25="","",ROUNDUP(E25/IF($H$5<>"",$H$5,$E$5),0)) -> 2
A27: 年小保养成本 / Annual Minor Service Cost | E27: =IF(E26="","",E26*((IF($H$6<>"",$H$6,$E$6)*IF($H$12<>"",$H$12,$E$12))+(IF($H$7<>"",$H$7,$E$7)*IF($H$8<>"",$H$8,$E$8))+IF($H$9<>"",$H$9,$E$9)+IF($H$10<>"",$H$10,$E$10))) -> 545.6
A28: 年空气滤芯成本 / Annual Air Filter Cost | E28: =IF(E25="","",IF(IF($H$13<>"",$H$13,$E$13)="",ROUNDUP(E26/2,0)*IF($H$11<>"",$H$11,$E$11),ROUNDUP(E25/IF($H$13<>"",$H$13,$E$13),0)*IF($H$11<>"",$H$11,$E$11))) -> 30
A29: 年冷却液成本 / Annual Coolant Cost | E29: =IF(OR(IF($H$14<>"",$H$14,$E$14)="",IF($H$14<>"",$H$14,$E$14)<=0),"",((IF($H$15<>"",$H$15,$E$15)*IF($H$16<>"",$H$16,$E$16))+(IF($H$17<>"",$H$17,$E$17)*IF($H$12<>"",$H$12,$E$12)))/IF($H$14<>"",$H$14,$E$14)) -> 77.5
A30: 年启动电池成本 / Annual Starter Battery Cost | E30: =IF(OR(IF($H$18<>"",$H$18,$E$18)="",IF($H$18<>"",$H$18,$E$18)<=0),"",(IF($H$19<>"",$H$19,$E$19)+(IF($H$20<>"",$H$20,$E$20)*IF($H$12<>"",$H$12,$E$12)))/IF($H$18<>"",$H$18,$E$18)) -> 85
A31: 年度保养费用合计 / Annual Maintenance Total | E31: =SUM(E27:E30) -> 738.1

Sheet 11_汇总看板
A1: 项目成本汇总看板 / Project Cost Dashboard
A3: 项目概览 / Project Overview
A4: 项目名称 / Project Name | B4: 国家/地区 / Country-Region | C4: 报价日期 / Quotation Date | D4: 基准币种 / Base Currency | E4: 项目阶段 / Project Stage | F4: 项目备注 / Project Notes
A5: =IF('01_项目基础信息'!B5="","",'01_项目基础信息'!B5) -> MGS微电网售前方案 | B5: =IF('01_项目基础信息'!B7="","",'01_项目基础信息'!B7) -> 美国 | C5: =IF('01_项目基础信息'!B9="","",'01_项目基础信息'!B9) -> 46094 | D5: =IF('01_项目基础信息'!B19="","",'01_项目基础信息'!B19) -> 美元 / USD | E5: =IF('01_项目基础信息'!B10="","",'01_项目基础信息'!B10) -> 售前初算 / Early Estimate | F5: =IF('01_项目基础信息'!B21="","",'01_项目基础信息'!B21)
A8: 关键汇总 / Key Summary
A9: 指标 / KPI | B9: 数值 / Value | C9: 单位 / Unit | D9: 取数逻辑 / Source Logic | E9: 检查说明 / Review Notes | F9: 状态 / Status
A10: 一次性总成本 CAPEX / Total CAPEX | B10: =IF('02_CAPEX汇总'!D11="","",'02_CAPEX汇总'!D11) -> 268128.8 | C10: 美元 / USD | D10: 来自 CAPEX 汇总 / From CAPEX Summary | E10: 重点看是否明显偏低/偏高 / Check for unusually low/high total
A11: 年度固定费用 OPEX / Annual Fixed OPEX | B11: =IF('08_年度成本_OPEX'!K12="","",'08_年度成本_OPEX'!K12) -> 4938.1 | C11: 美元/年 / USD/year | D11: 来自 OPEX 合计 / From OPEX Total
A12: 柴油单价 / Diesel Price | B12: =IF('09_柴油与能源参数'!E5="","",'09_柴油与能源参数'!E5) -> 0.95 | C12: 美元/升 / USD/L | D12: 来自柴油参数首行 / From Fuel Parameters
A13: 光伏规模 / PV Size | B13: =IF('01_项目基础信息'!B14="","",'01_项目基础信息'!B14) -> 83.84 | C13: kWp | D13: 基础信息 / Project Basics
A14: 储能规模 / BESS Size | B14: =IF('01_项目基础信息'!B15="","",'01_项目基础信息'!B15) -> 257.28 | C14: kWh | D14: 基础信息 / Project Basics
A15: 柴油机容量 / Diesel Size | B15: =IF('01_项目基础信息'!B16="","",'01_项目基础信息'!B16) -> 40 | C15: kW | D15: 基础信息 / Project Basics
A16: 已填 CAPEX 明细行数 / Filled CAPEX Line Items | B16: =COUNTIF('03_光伏系统明细'!P5:P12,">0")+COUNTIF('04_储能系统明细'!P5:P13,">0")+COUNTIF('05_柴油机系统明细'!P5:P10,">0")+COUNTIF('06_电气配套明细'!P5:P12,">0")+COUNTIF('07_运输安装其他'!P5:P12,">0") -> 12 | C16: 行 | D16: 用于判断是否已拆够细 / Indicates input detail level

Sheet 12_历史项目参考
A1: 成本统计
A2: 序号 /numerical orde | B2: 分类 / Category | C2: 成本项目 / Cost Item | D2: 价格（含税）/ Price (incl. tax) | E2: 备注 / Remarks
A3: 1 | B3: 初始成本 / Initial cost | C3: 光伏组件（含运输） PV module package (incl. transportation) | D3: '=0.32*41.92*2*1000 | E3: 组件按单瓦 0.32 美元/瓦；Module price calculated at $0.32/W
A4: 2 | B4: 初始成本 / Initial cost | C4: 光伏支架 PV mounting structure | D4: '=12700*4*1.5 | E4: 含 50% 关税；Includes 50% import duty
A5: 3 | B5: 初始成本 / Initial cost | C5: 储能系统（含运输） Energy storage system (incl. transportation) | D5: '=3*7500+16*3100+4000 | E5: 逆变器+电池包+托盘 =（3×7,500 + 16×3,100 + 4,000）；Inverters + battery packs + pallets = (3×7,500 + 16×3,100 + 4,000)
A6: 4 | B6: 初始成本 / Initial cost | C6: 柴油发电机 Diesel generator set | D6: 45000
A7: 5 | B7: 初始成本 / Initial cost | C7: 国际运输 International transportation | D7: '=3600*3 | E7: 国内零件运输 —— 国外项目运输；Domestic component transport—— overseas project delivery
A8: 6 | B8: 初始成本 / Initial cost | C8: 一次性全部安装费用 One-time full installation cost | D8: '=5000 | E8: 工人 5 人，每人每天 400 美元；Five workers, $400 per worker per day
A9: 7 | B9: 初始成本 / Initial cost | C9: 其他配件费用 Other accessory costs | D9: '=26000+500+500+1000+200+300 | E9: 配电箱(26,000)、直流线缆(500+500+1000)、交流线缆(200)、电池辅材(300)；Distribution box (26,000), DC cables (500+500+1000), AC cables (200), battery accessories (300)
A10: 8 | B10: 微电网运维费用 / Microgrid O&M | C10: 微电网运维费用（年） PV & storage O&M cost (per year) | D10: 1000 | E10: ——
A11: 9 | B11: 微电网运维费用 / Microgrid O&M | C11: 设备维修费用（年） Equipment repair cost (per year) | D11: 200 | E11: ——
A12: 10 | B12: 微电网运维费用 / Microgrid O&M | C12: 保险费用（年） Insurance cost (per year) | D12: 3000 | E12: 具体金额需咨询保险公司；Exact amount to be confirmed with insurance company
A13: 15 | B13: 柴油消耗 /diesel consumption | C13: 柴油单价（每升） Diesel price per liter | D13: 0.95 | E13: 可根据国际油价调整；It can be adjusted according to international oil prices
A14: 24 | B14: 柴油发电机运维 / Diesel generator O&M | C14: 小保养间隔h (S_oil) | D14: 250 | E14: 每隔该小时执行小保养（换油+燃油滤）；Minor service interval in hours (engine oil + fuel filter replacement)
A15: 25 | B15: 柴油发电机运维 / Diesel generator O&M | C15: 每次保养工时h (t_pm) | D15: 1.5 | E15: 小保养人工时（更换机油/滤芯、检查）；Labor hours per minor service (oil/filter replacement, inspection)
A16: 26 | B16: 柴油发电机运维 / Diesel generator O&M | C16: 每次换油量gal (V_oil) | D16: 2.15 | E16: 每次小保养更换机油量；Engine oil volume replaced per minor service
A17: 27 | B17: 柴油发电机运维 / Diesel generator O&M | C17: 机油 $/gal (P_oil) | D17: 22 | E17: 机油单价；Unit price of engine oil ($/gal)
A18: 28 | B18: 柴油发电机运维 / Diesel generator O&M | C18: 机油滤芯$ (C_of) | D18: 18 | E18: 机油滤芯价格；Price of engine oil filter
A19: 29 | B19: 柴油发电机运维 / Diesel generator O&M | C19: 柴油滤芯$ (C_ff) | D19: 20 | E19: 燃油滤芯价格；Price of diesel fuel filter
A20: 30 | B20: 柴油发电机运维 / Diesel generator O&M | C20: 空气滤芯$ (C_af) | D20: 30 | E20: 空气滤芯价格（默认：每2次PM换1只）；Price of air filter (default: one filter every 2 PM services)
A21: 31 | B21: 柴油发电机运维 / Diesel generator O&M | C21: 人工 $/h (labor_rate) | D21: 125 | E21: 维保人工费率（$/小时）；Maintenance labor rate ($/h)
... A29: 39 | B29: 柴油发电机运维 / Diesel generator O&M | C29: 电池工时h (battery_labor_hours) | D29: 0.5 | E29: 更换电池人工时；Labor hours per battery replacement
A31: 说明：这一页保留你上传的历史项目成本表内容，公式已转成文本，仅作为参考。 / Note: This sheet preserves your uploaded historical cost table. Formulas are converted to text and kept for reference only.

Sheet 99_下拉选项
A1: 是 / Yes | B1: 美元 / USD | C1: 售前初算 / Early Estimate | D1: 必填 / Required | E1: 光伏系统 / PV System | F1: 组件 / Module
A2: 否 / No | B2: 人民币 / CNY | C2: 客户沟通中 / In Discussion | D2: 建议填 / Recommended | E2: 储能系统 / BESS System | F2: 逆变器 / Inverter
B3: 欧元 / EUR | C3: 报价确认中 / Quotation Review | D3: 选填 / Optional | E3: 柴油机系统 / Diesel System | F3: 支架 / Mounting
B4: 英镑 / GBP | C4: 已提交 / Submitted | E4: 电气配套 / Electrical Balance | F4: 汇流箱/配电箱 / Combiner-Switchboard
B5: 日元 / JPY | C5: 中标后复盘 / Post-Award Review | E5: 运输安装其他 / Logistics & Installation | F5: 连接器/辅材 / Connectors-Auxiliary
B6: 自定义 / Custom | E6: 年度成本 / Annual OPEX | F6: PCS / PCS
F7: 光储一体化托盘/PV-ESS Integrated Pallet
F8: 电池包 / Battery Pack
F9: 电池柜/集装箱 / Battery Cabinet-Container
F10: BMS/EMS / BMS-EMS
F11: HVAC/消防 / HVAC-Fire
F12: 柴油发电机 / Diesel Generator
F13: 油箱/ATS / Tank-ATS
F14: 变压器 / Transformer
F15: 开关柜 / Switchgear
F16: AC电缆 / AC Cable
F17: DC电缆 / DC Cable
F18: 通信监控 / Communication-SCADA
... F24: 其他 / Other
